revision/__init__.py
revision/archiver.py
revision/cli.py
revision/client.py
revision/client_manager.py
revision/config.py
revision/constants.py
revision/data.py
revision/decorators.py
revision/exceptions.py
revision/file_transfer.py
revision/history.py
revision/mixins.py
revision/orchestrator.py
revision/state.py
revision/test.py
revision/util.py
revision-0.1.1.dist-info/DESCRIPTION.rst
revision-0.1.1.dist-info/METADATA
revision-0.1.1.dist-info/RECORD
revision-0.1.1.dist-info/WHEEL
revision-0.1.1.dist-info/entry_points.txt
revision-0.1.1.dist-info/metadata.json
revision-0.1.1.dist-info/top_level.txt
