Metadata-Version: 2.0
Name: revision
Version: 0.1.1
Summary: Static assets revisioning library.
Home-page: https://github.com/COLORFULBOARD/revision
Author: SENSY Inc.
Author-email: UNKNOWN
License: MIT
Platform: UNKNOWN
Classifier: Development Status :: 4 - Beta
Classifier: Environment :: Web Environment
Classifier: License :: OSI Approved :: MIT License
Classifier: Operating System :: OS Independent
Classifier: Programming Language :: Python
Classifier: Programming Language :: Python :: 2
Classifier: Programming Language :: Python :: 2.7
Classifier: Programming Language :: Python :: 3
Classifier: Programming Language :: Python :: 3.6
Classifier: Topic :: Software Development :: Libraries :: Python Modules
Requires-Dist: click (==6.7)
Requires-Dist: requests (==2.18.4)
Requires-Dist: six (==1.11.0)
Provides-Extra: dev
Requires-Dist: flake8 (==3.5.0); extra == 'dev'
Requires-Dist: pytest (==3.3.1); extra == 'dev'
Requires-Dist: tox (==2.9.1); extra == 'dev'
